src/__init__.py
src/catalog.py
src/ncml.py
src/data/catalog.xml.j2
src/data/esgf.ncml.j2
tdspu/__init__.py
tdspu/catalog.py
tdspu/csvify
tdspu/ncml.py
tdspu/ncmlify
tdspu/data/catalog.xml.j2
tdspu/data/esgf.ncml.j2
tdspu-0.16.data/scripts/csvify
tdspu-0.16.data/scripts/ncmlify
tdspu-0.16.dist-info/METADATA
tdspu-0.16.dist-info/WHEEL
tdspu-0.16.dist-info/entry_points.txt
tdspu-0.16.dist-info/top_level.txt
tdspu-0.16.dist-info/RECORD
