Metadata-Version: 2.1
Name: tdspu
Version: 0.16
Summary: Utils for NcML and TDS catalog generation
Home-page: UNKNOWN
Author: zequihg50
Author-email: ezequiel.cimadevilla@unican.es
License: UNKNOWN
Platform: UNKNOWN
Requires-Python: >=3
Requires-Dist: netCDF4
Requires-Dist: Jinja2
Requires-Dist: pandas
